{
    "id": 11107867,
    "name": "AKlevenseven",
    "avatar url": "https://a.ppy.sh/11107867?1745171349.jpeg",
    "days ago": 0,
    "tracking": true,
    "beatmapsets": {},
    "beatmap plays history": {},
    "scores": {
        "11107867241009132720": {
            "uid": 11107867,
            "bid": 2759257,
            "time": "241009132720",
            "mods": [
                "CL"
            ],
            "combo": 476,
            "passed": true,
            "pp": null,
            "acc": 0.9542715730578868,
            "grade": "S",
            "score": 809560,
            "320": 1030,
            "300": 375,
            "200": 98,
            "100": 20,
            "50": 7,
            "0": 19
        },
        "11107867241009131404": {
            "uid": 11107867,
            "bid": 2759261,
            "time": "241009131404",
            "mods": [
                "CL"
            ],
            "combo": 897,
            "passed": true,
            "pp": null,
            "acc": 0.9957212713936431,
            "grade": "S",
            "score": 981225,
            "320": 1347,
            "300": 274,
            "200": 11,
            "100": 1,
            "50": 2,
            "0": 1
        },
        "11107867241009131114": {
            "uid": 11107867,
            "bid": 2759261,
            "time": "241009131114",
            "mods": [
                "CL"
            ],
            "combo": 820,
            "passed": true,
            "pp": null,
            "acc": 0.9933781581092095,
            "grade": "S",
            "score": 968807,
            "320": 1299,
            "300": 313,
            "200": 19,
            "100": 0,
            "50": 3,
            "0": 2
        },
        "11107867241009133053": {
            "uid": 11107867,
            "bid": 2759266,
            "time": "241009133053",
            "mods": [
                "CL"
            ],
            "combo": 2381,
            "passed": true,
            "pp": null,
            "acc": 0.99528672427337,
            "grade": "S",
            "score": 977985,
            "320": 2014,
            "300": 504,
            "200": 22,
            "100": 4,
            "50": 0,
            "0": 2
        },
        "11107867241009131830": {
            "uid": 11107867,
            "bid": 2759268,
            "time": "241009131830",
            "mods": [
                "CL"
            ],
            "combo": 1014,
            "passed": true,
            "pp": null,
            "acc": 0.976854659389529,
            "grade": "S",
            "score": 874836,
            "320": 2193,
            "300": 949,
            "200": 112,
            "100": 13,
            "50": 4,
            "0": 27
        },
        "11107867241009133438": {
            "uid": 11107867,
            "bid": 2759272,
            "time": "241009133438",
            "mods": [
                "CL"
            ],
            "combo": 846,
            "passed": true,
            "pp": null,
            "acc": 0.9743589743589743,
            "grade": "S",
            "score": 881565,
            "320": 1814,
            "300": 1018,
            "200": 152,
            "100": 15,
            "50": 2,
            "0": 15
        },
        "11107867250221133350": {
            "uid": 11107867,
            "bid": 1577244,
            "time": "250221133350",
            "mods": [
                "CL"
            ],
            "combo": 832,
            "passed": true,
            "pp": null,
            "acc": 0.9939606467952464,
            "grade": "S",
            "score": 956294,
            "320": 1352,
            "300": 339,
            "200": 14,
            "100": 1,
            "50": 0,
            "0": 5
        }
    }
}