{
    "id": 12763134,
    "name": "timing",
    "avatar url": "https://a.ppy.sh/12763134?1669120664.jpeg",
    "days ago": 0,
    "tracking": true,
    "beatmapsets": {},
    "beatmap plays history": {},
    "scores": {
        "12763134250429164135": {
            "uid": 12763134,
            "bid": 4984355,
            "time": "250429164135",
            "mods": [
                "CL"
            ],
            "combo": 84,
            "passed": true,
            "pp": 32.1522,
            "acc": 0.8960848884010245,
            "grade": "B",
            "score": 598859,
            "320": 402,
            "300": 356,
            "200": 78,
            "100": 17,
            "50": 4,
            "0": 54
        },
        "12763134250416130100": {
            "uid": 12763134,
            "bid": 4984408,
            "time": "250416130100",
            "mods": [
                "CL"
            ],
            "combo": 258,
            "passed": true,
            "pp": 30.4959,
            "acc": 0.9654654654654654,
            "grade": "S",
            "score": 829282,
            "320": 442,
            "300": 189,
            "200": 17,
            "100": 1,
            "50": 2,
            "0": 15
        },
        "12763134250416125707": {
            "uid": 12763134,
            "bid": 4984408,
            "time": "250416125707",
            "mods": [
                "CL"
            ],
            "combo": 252,
            "passed": true,
            "pp": 27.109,
            "acc": 0.9522022022022022,
            "grade": "S",
            "score": 812081,
            "320": 401,
            "300": 215,
            "200": 24,
            "100": 5,
            "50": 3,
            "0": 18
        },
        "12763134250503090933": {
            "uid": 12763134,
            "bid": 4984408,
            "time": "250503090933",
            "mods": [
                "CL"
            ],
            "combo": 148,
            "passed": true,
            "pp": 27.4116,
            "acc": 0.954954954954955,
            "grade": "S",
            "score": 776468,
            "320": 389,
            "300": 220,
            "200": 37,
            "100": 7,
            "50": 0,
            "0": 13
        },
        "12763134250503090755": {
            "uid": 12763134,
            "bid": 4984408,
            "time": "250503090755",
            "mods": [
                "CL"
            ],
            "combo": 170,
            "passed": true,
            "pp": 27.9484,
            "acc": 0.9567067067067067,
            "grade": "S",
            "score": 770403,
            "320": 399,
            "300": 220,
            "200": 26,
            "100": 2,
            "50": 1,
            "0": 18
        },
        "12763134250416125508": {
            "uid": 12763134,
            "bid": 4984408,
            "time": "250416125508",
            "mods": [
                "CL"
            ],
            "combo": 185,
            "passed": true,
            "pp": 26.1818,
            "acc": 0.9479479479479479,
            "grade": "A",
            "score": 758661,
            "320": 396,
            "300": 221,
            "200": 18,
            "100": 6,
            "50": 2,
            "0": 23
        },
        "12763134250411024319": {
            "uid": 12763134,
            "bid": 4984408,
            "time": "250411024319",
            "mods": [
                "CL"
            ],
            "combo": 175,
            "passed": true,
            "pp": 27.0114,
            "acc": 0.9512012012012012,
            "grade": "S",
            "score": 752378,
            "320": 406,
            "300": 214,
            "200": 17,
            "100": 6,
            "50": 1,
            "0": 22
        },
        "12763134250407125640": {
            "uid": 12763134,
            "bid": 4984408,
            "time": "250407125640",
            "mods": [
                "CL"
            ],
            "combo": 95,
            "passed": true,
            "pp": 25.9963,
            "acc": 0.9466966966966966,
            "grade": "A",
            "score": 731897,
            "320": 399,
            "300": 213,
            "200": 27,
            "100": 1,
            "50": 1,
            "0": 25
        },
        "12763134250412051707": {
            "uid": 12763134,
            "bid": 4984408,
            "time": "250412051707",
            "mods": [
                "CL"
            ],
            "combo": 122,
            "passed": true,
            "pp": 23.9954,
            "acc": 0.9344344344344344,
            "grade": "A",
            "score": 723078,
            "320": 419,
            "300": 179,
            "200": 31,
            "100": 9,
            "50": 4,
            "0": 24
        },
        "12763134250407022102": {
            "uid": 12763134,
            "bid": 4984408,
            "time": "250407022102",
            "mods": [
                "CL"
            ],
            "combo": 110,
            "passed": true,
            "pp": 22.951,
            "acc": 0.9331831831831832,
            "grade": "A",
            "score": 702131,
            "320": 378,
            "300": 221,
            "200": 32,
            "100": 3,
            "50": 1,
            "0": 31
        },
        "12763134250407021812": {
            "uid": 12763134,
            "bid": 4984408,
            "time": "250407021812",
            "mods": [
                "CL"
            ],
            "combo": 70,
            "passed": true,
            "pp": 24.2882,
            "acc": 0.9379379379379379,
            "grade": "A",
            "score": 683561,
            "320": 399,
            "300": 208,
            "200": 23,
            "100": 6,
            "50": 2,
            "0": 28
        },
        "12763134250407021536": {
            "uid": 12763134,
            "bid": 4984408,
            "time": "250407021536",
            "mods": [
                "CL"
            ],
            "combo": 95,
            "passed": true,
            "pp": 22.1799,
            "acc": 0.9269269269269269,
            "grade": "A",
            "score": 688168,
            "320": 401,
            "300": 192,
            "200": 35,
            "100": 2,
            "50": 2,
            "0": 34
        },
        "12763134250412051459": {
            "uid": 12763134,
            "bid": 4984408,
            "time": "250412051459",
            "mods": [
                "CL"
            ],
            "combo": 155,
            "passed": true,
            "pp": 19.9252,
            "acc": 0.9176676676676677,
            "grade": "A",
            "score": 692608,
            "320": 378,
            "300": 211,
            "200": 28,
            "100": 9,
            "50": 3,
            "0": 37
        },
        "12763134250406020858": {
            "uid": 12763134,
            "bid": 4984408,
            "time": "250406020858",
            "mods": [
                "CL"
            ],
            "combo": 125,
            "passed": true,
            "pp": 21.3405,
            "acc": 0.9219219219219219,
            "grade": "A",
            "score": 673520,
            "320": 408,
            "300": 179,
            "200": 36,
            "100": 8,
            "50": 2,
            "0": 33
        },
        "12763134250405023657": {
            "uid": 12763134,
            "bid": 4984408,
            "time": "250405023657",
            "mods": [
                "CL"
            ],
            "combo": 99,
            "passed": true,
            "pp": 20.3547,
            "acc": 0.9261761761761762,
            "grade": "A",
            "score": 665185,
            "320": 315,
            "300": 274,
            "200": 39,
            "100": 5,
            "50": 1,
            "0": 32
        },
        "12763134250407021318": {
            "uid": 12763134,
            "bid": 4984408,
            "time": "250407021318",
            "mods": [
                "CL"
            ],
            "combo": 69,
            "passed": true,
            "pp": 19.6617,
            "acc": 0.914914914914915,
            "grade": "A",
            "score": 639421,
            "320": 392,
            "300": 183,
            "200": 47,
            "100": 8,
            "50": 2,
            "0": 34
        },
        "12763134250413134649": {
            "uid": 12763134,
            "bid": 4984408,
            "time": "250413134649",
            "mods": [
                "CL"
            ],
            "combo": 86,
            "passed": true,
            "pp": 20.0912,
            "acc": 0.9209209209209209,
            "grade": "A",
            "score": 632033,
            "320": 354,
            "300": 217,
            "200": 57,
            "100": 12,
            "50": 2,
            "0": 24
        },
        "12763134250405023207": {
            "uid": 12763134,
            "bid": 4984408,
            "time": "250405023207",
            "mods": [
                "CL"
            ],
            "combo": 64,
            "passed": true,
            "pp": 17.0166,
            "acc": 0.9086586586586587,
            "grade": "A",
            "score": 611114,
            "320": 319,
            "300": 256,
            "200": 42,
            "100": 5,
            "50": 3,
            "0": 41
        },
        "12763134250411023728": {
            "uid": 12763134,
            "bid": 1683798,
            "time": "250411023728",
            "mods": [
                "CL"
            ],
            "combo": 191,
            "passed": true,
            "pp": null,
            "acc": 0.9600355239786856,
            "grade": "S",
            "score": 781581,
            "320": 333,
            "300": 200,
            "200": 10,
            "100": 2,
            "50": 1,
            "0": 17
        },
        "12763134250406024938": {
            "uid": 12763134,
            "bid": 1683798,
            "time": "250406024938",
            "mods": [
                "CL"
            ],
            "combo": 128,
            "passed": true,
            "pp": null,
            "acc": 0.9396092362344582,
            "grade": "A",
            "score": 729399,
            "320": 318,
            "300": 202,
            "200": 12,
            "100": 2,
            "50": 2,
            "0": 27
        },
        "12763134250411023532": {
            "uid": 12763134,
            "bid": 1683798,
            "time": "250411023532",
            "mods": [
                "CL"
            ],
            "combo": 107,
            "passed": true,
            "pp": null,
            "acc": 0.9410894020130255,
            "grade": "A",
            "score": 697615,
            "320": 319,
            "300": 191,
            "200": 25,
            "100": 9,
            "50": 1,
            "0": 18
        },
        "12763134250411023326": {
            "uid": 12763134,
            "bid": 1683798,
            "time": "250411023326",
            "mods": [
                "CL"
            ],
            "combo": 194,
            "passed": true,
            "pp": null,
            "acc": 0.9396092362344582,
            "grade": "A",
            "score": 693770,
            "320": 324,
            "300": 191,
            "200": 19,
            "100": 4,
            "50": 0,
            "0": 25
        },
        "12763134250405020709": {
            "uid": 12763134,
            "bid": 1683798,
            "time": "250405020709",
            "mods": [
                "CL"
            ],
            "combo": 119,
            "passed": true,
            "pp": null,
            "acc": 0.9310242747187685,
            "grade": "A",
            "score": 693168,
            "320": 255,
            "300": 253,
            "200": 22,
            "100": 4,
            "50": 1,
            "0": 28
        },
        "12763134250406024744": {
            "uid": 12763134,
            "bid": 1683798,
            "time": "250406024744",
            "mods": [
                "CL"
            ],
            "combo": 128,
            "passed": true,
            "pp": null,
            "acc": 0.923919478981646,
            "grade": "A",
            "score": 678005,
            "320": 289,
            "300": 218,
            "200": 16,
            "100": 7,
            "50": 1,
            "0": 32
        },
        "12763134250326220655": {
            "uid": 12763134,
            "bid": 1683798,
            "time": "250326220655",
            "mods": [
                "CL"
            ],
            "combo": 109,
            "passed": true,
            "pp": null,
            "acc": 0.9218472468916519,
            "grade": "A",
            "score": 667859,
            "320": 250,
            "300": 252,
            "200": 22,
            "100": 5,
            "50": 4,
            "0": 30
        },
        "12763134250326220917": {
            "uid": 12763134,
            "bid": 1683798,
            "time": "250326220917",
            "mods": [
                "CL"
            ],
            "combo": 136,
            "passed": true,
            "pp": null,
            "acc": 0.9265837773830669,
            "grade": "A",
            "score": 662879,
            "320": 245,
            "300": 260,
            "200": 22,
            "100": 5,
            "50": 2,
            "0": 29
        },
        "12763134250326220511": {
            "uid": 12763134,
            "bid": 1683798,
            "time": "250326220511",
            "mods": [
                "CL"
            ],
            "combo": 140,
            "passed": true,
            "pp": null,
            "acc": 0.9245115452930728,
            "grade": "A",
            "score": 646402,
            "320": 254,
            "300": 245,
            "200": 28,
            "100": 8,
            "50": 1,
            "0": 27
        },
        "12763134250326221118": {
            "uid": 12763134,
            "bid": 1683798,
            "time": "250326221118",
            "mods": [
                "CL"
            ],
            "combo": 114,
            "passed": true,
            "pp": null,
            "acc": 0.9082297217288336,
            "grade": "A",
            "score": 641280,
            "320": 239,
            "300": 249,
            "200": 31,
            "100": 8,
            "50": 0,
            "0": 36
        },
        "12763134250326023436": {
            "uid": 12763134,
            "bid": 1683798,
            "time": "250326023436",
            "mods": [
                "CL"
            ],
            "combo": 115,
            "passed": true,
            "pp": null,
            "acc": 0.9079336885731202,
            "grade": "A",
            "score": 635736,
            "320": 233,
            "300": 259,
            "200": 24,
            "100": 9,
            "50": 1,
            "0": 37
        },
        "12763134250326023217": {
            "uid": 12763134,
            "bid": 1683798,
            "time": "250326023217",
            "mods": [
                "CL"
            ],
            "combo": 56,
            "passed": true,
            "pp": null,
            "acc": 0.8913558318531676,
            "grade": "B",
            "score": 578606,
            "320": 261,
            "300": 219,
            "200": 28,
            "100": 8,
            "50": 3,
            "0": 44
        },
        "12763134250324022317": {
            "uid": 12763134,
            "bid": 1683798,
            "time": "250324022317",
            "mods": [
                "CL"
            ],
            "combo": 87,
            "passed": true,
            "pp": null,
            "acc": 0.8688573120189461,
            "grade": "B",
            "score": 537689,
            "320": 171,
            "300": 287,
            "200": 44,
            "100": 5,
            "50": 1,
            "0": 55
        },
        "12763134250324143402": {
            "uid": 12763134,
            "bid": 1683798,
            "time": "250324143402",
            "mods": [
                "CL"
            ],
            "combo": 51,
            "passed": true,
            "pp": null,
            "acc": 0.822380106571936,
            "grade": "B",
            "score": 506317,
            "320": 242,
            "300": 184,
            "200": 48,
            "100": 13,
            "50": 4,
            "0": 72
        },
        "12763134250323095204": {
            "uid": 12763134,
            "bid": 1683798,
            "time": "250323095204",
            "mods": [
                "CL"
            ],
            "combo": 61,
            "passed": true,
            "pp": null,
            "acc": 0.7841918294849023,
            "grade": "C",
            "score": 459217,
            "320": 106,
            "300": 292,
            "200": 62,
            "100": 4,
            "50": 5,
            "0": 94
        },
        "12763134250321161156": {
            "uid": 12763134,
            "bid": 1683798,
            "time": "250321161156",
            "mods": [
                "CL"
            ],
            "combo": 30,
            "passed": true,
            "pp": null,
            "acc": 0.7513321492007105,
            "grade": "C",
            "score": 441349,
            "320": 161,
            "300": 223,
            "200": 50,
            "100": 15,
            "50": 4,
            "0": 110
        },
        "12763134250322020038": {
            "uid": 12763134,
            "bid": 1683798,
            "time": "250322020038",
            "mods": [
                "CL"
            ],
            "combo": 40,
            "passed": true,
            "pp": null,
            "acc": 0.7374185908821788,
            "grade": "C",
            "score": 441497,
            "320": 173,
            "300": 215,
            "200": 33,
            "100": 14,
            "50": 3,
            "0": 125
        },
        "12763134250416125243": {
            "uid": 12763134,
            "bid": 1683801,
            "time": "250416125243",
            "mods": [
                "CL"
            ],
            "combo": 166,
            "passed": true,
            "pp": null,
            "acc": 0.9417831004657352,
            "grade": "A",
            "score": 695872,
            "320": 254,
            "300": 203,
            "200": 18,
            "100": 6,
            "50": 5,
            "0": 15
        },
        "12763134250418005349": {
            "uid": 12763134,
            "bid": 1683801,
            "time": "250418005349",
            "mods": [
                "CL"
            ],
            "combo": 164,
            "passed": true,
            "pp": null,
            "acc": 0.9128409846972722,
            "grade": "A",
            "score": 659184,
            "320": 272,
            "300": 169,
            "200": 19,
            "100": 7,
            "50": 8,
            "0": 26
        },
        "12763134250416125045": {
            "uid": 12763134,
            "bid": 1683801,
            "time": "250416125045",
            "mods": [
                "CL"
            ],
            "combo": 147,
            "passed": true,
            "pp": null,
            "acc": 0.908183632734531,
            "grade": "A",
            "score": 635931,
            "320": 233,
            "300": 204,
            "200": 22,
            "100": 8,
            "50": 4,
            "0": 30
        },
        "12763134250511123045": {
            "uid": 12763134,
            "bid": 5029128,
            "time": "250511123045",
            "mods": [
                "CL"
            ],
            "combo": 395,
            "passed": true,
            "pp": 44.7182,
            "acc": 0.9813319878910192,
            "grade": "S",
            "score": 887602,
            "320": 701,
            "300": 260,
            "200": 14,
            "100": 6,
            "50": 1,
            "0": 9
        },
        "12763134250503101156": {
            "uid": 12763134,
            "bid": 5029128,
            "time": "250503101156",
            "mods": [
                "CL"
            ],
            "combo": 247,
            "passed": true,
            "pp": 39.6087,
            "acc": 0.9700639085099226,
            "grade": "S",
            "score": 849996,
            "320": 571,
            "300": 365,
            "200": 34,
            "100": 6,
            "50": 4,
            "0": 11
        }
    }
}