{
    "id": 14593851,
    "name": "Naltazarr",
    "avatar url": "https://a.ppy.sh/14593851?1562871370.jpeg",
    "days ago": 0,
    "tracking": true,
    "beatmapsets": {},
    "beatmap plays history": {},
    "scores": {
        "14593851241019222829": {
            "uid": 14593851,
            "bid": 2759274,
            "time": "241019222829",
            "mods": [
                "DT",
                "NF",
                "CL"
            ],
            "combo": 3,
            "passed": true,
            "pp": null,
            "acc": 0.008842175508842176,
            "grade": "D",
            "score": 2198,
            "320": 1,
            "300": 3,
            "200": 5,
            "100": 2,
            "50": 5,
            "0": 983
        }
    }
}