{
    "id": 16265710,
    "name": "Scol1t",
    "avatar url": "https://a.ppy.sh/16265710?1649010002.png",
    "days ago": 0,
    "tracking": true,
    "beatmapsets": {},
    "beatmap plays history": {},
    "scores": {
        "16265710250303012140": {
            "uid": 16265710,
            "bid": 4974665,
            "time": "250303012140",
            "mods": [
                "CL"
            ],
            "combo": 22,
            "passed": true,
            "pp": 0.626691,
            "acc": 0.8533333333333334,
            "grade": "B",
            "score": 535849,
            "320": 127,
            "300": 92,
            "200": 23,
            "100": 1,
            "50": 0,
            "0": 32
        },
        "16265710250303133303": {
            "uid": 16265710,
            "bid": 4174562,
            "time": "250303133303",
            "mods": [
                "CL"
            ],
            "combo": 57,
            "passed": true,
            "pp": 0.0,
            "acc": 0.8184523809523809,
            "grade": "B",
            "score": 522408,
            "320": 35,
            "300": 47,
            "200": 13,
            "100": 3,
            "50": 0,
            "0": 14
        },
        "16265710250303010922": {
            "uid": 16265710,
            "bid": 4174562,
            "time": "250303010922",
            "mods": [
                "CL"
            ],
            "combo": 57,
            "passed": true,
            "pp": 0.0,
            "acc": 0.7901785714285714,
            "grade": "C",
            "score": 482339,
            "320": 40,
            "300": 39,
            "200": 12,
            "100": 4,
            "50": 1,
            "0": 16
        },
        "16265710250303133212": {
            "uid": 16265710,
            "bid": 4174562,
            "time": "250303133212",
            "mods": [
                "CL"
            ],
            "combo": 53,
            "passed": true,
            "pp": 0.0,
            "acc": 0.7619047619047619,
            "grade": "C",
            "score": 470221,
            "320": 36,
            "300": 43,
            "200": 8,
            "100": 3,
            "50": 0,
            "0": 22
        }
    }
}