{
    "id": 26820084,
    "name": "- AteF -",
    "avatar url": "https://a.ppy.sh/26820084?1747086383.jpeg",
    "days ago": 0,
    "tracking": true,
    "beatmapsets": {},
    "beatmap plays history": {},
    "scores": {
        "26820084250427231924": {
            "uid": 26820084,
            "bid": 4862376,
            "time": "250427231924",
            "mods": [
                "CL"
            ],
            "combo": 808,
            "passed": true,
            "pp": 130.692,
            "acc": 0.9873553941350551,
            "grade": "S",
            "score": 943920,
            "320": 1013,
            "300": 197,
            "200": 18,
            "100": 3,
            "50": 2,
            "0": 6
        },
        "26820084250302002513": {
            "uid": 26820084,
            "bid": 4862376,
            "time": "250302002513",
            "mods": [
                "CL"
            ],
            "combo": 608,
            "passed": true,
            "pp": 123.158,
            "acc": 0.9795534032822169,
            "grade": "S",
            "score": 917585,
            "320": 956,
            "300": 239,
            "200": 23,
            "100": 7,
            "50": 6,
            "0": 8
        }
    }
}