{
    "id": 34470188,
    "name": "stevegamer68",
    "avatar url": "https://osu.ppy.sh/images/layout/avatar-guest@2x.png",
    "days ago": 0,
    "tracking": true,
    "beatmapsets": {},
    "beatmap plays history": {},
    "scores": {
        "34470188250312062310": {
            "uid": 34470188,
            "bid": 4981263,
            "time": "250312062310",
            "mods": [],
            "combo": 8,
            "passed": true,
            "pp": 0.0,
            "acc": 0.4727272727272727,
            "grade": "D",
            "score": 112145,
            "320": 10,
            "300": 12,
            "200": 5,
            "100": 2,
            "50": 0,
            "0": 26
        },
        "34470188250312061925": {
            "uid": 34470188,
            "bid": 4981263,
            "time": "250312061925",
            "mods": [],
            "combo": 5,
            "passed": true,
            "pp": 0.0,
            "acc": 0.41515151515151516,
            "grade": "D",
            "score": 86168,
            "320": 9,
            "300": 9,
            "200": 6,
            "100": 2,
            "50": 1,
            "0": 28
        }
    }
}