{
    "id": 6701104,
    "name": "Nene Sakura",
    "avatar url": "https://a.ppy.sh/6701104?1743538883.jpeg",
    "days ago": 0,
    "tracking": true,
    "beatmapsets": {},
    "beatmap plays history": {},
    "scores": {
        "6701104241008075420": {
            "uid": 6701104,
            "bid": 4705175,
            "time": "241008075420",
            "mods": [
                "CL"
            ],
            "combo": 163,
            "passed": true,
            "pp": 44.0553,
            "acc": 0.9404502541757443,
            "grade": "A",
            "score": 706527,
            "320": 393,
            "300": 428,
            "200": 62,
            "100": 1,
            "50": 4,
            "0": 30
        },
        "6701104241008064629": {
            "uid": 6701104,
            "bid": 4705176,
            "time": "241008064629",
            "mods": [
                "DT",
                "CL"
            ],
            "combo": 303,
            "passed": true,
            "pp": 30.368,
            "acc": 0.9894781144781145,
            "grade": "S",
            "score": 921951,
            "320": 311,
            "300": 77,
            "200": 5,
            "100": 1,
            "50": 1,
            "0": 1
        },
        "6701104241012115232": {
            "uid": 6701104,
            "bid": 4705177,
            "time": "241012115232",
            "mods": [
                "CL"
            ],
            "combo": 93,
            "passed": true,
            "pp": 44.2329,
            "acc": 0.885915867944622,
            "grade": "B",
            "score": 568116,
            "320": 482,
            "300": 529,
            "200": 134,
            "100": 20,
            "50": 13,
            "0": 74
        },
        "6701104241009115605": {
            "uid": 6701104,
            "bid": 4705177,
            "time": "241009115605",
            "mods": [
                "CL"
            ],
            "combo": 93,
            "passed": true,
            "pp": 40.0882,
            "acc": 0.8820553780617678,
            "grade": "B",
            "score": 553396,
            "320": 452,
            "300": 556,
            "200": 134,
            "100": 16,
            "50": 10,
            "0": 84
        },
        "6701104241012115029": {
            "uid": 6701104,
            "bid": 4705177,
            "time": "241012115029",
            "mods": [
                "CL"
            ],
            "combo": 93,
            "passed": true,
            "pp": 38.9964,
            "acc": 0.880457933972311,
            "grade": "B",
            "score": 553844,
            "320": 455,
            "300": 549,
            "200": 136,
            "100": 16,
            "50": 14,
            "0": 82
        },
        "6701104241012111734": {
            "uid": 6701104,
            "bid": 4705178,
            "time": "241012111734",
            "mods": [
                "DT",
                "CL"
            ],
            "combo": 159,
            "passed": true,
            "pp": 41.4951,
            "acc": 0.9364599092284418,
            "grade": "A",
            "score": 690603,
            "320": 270,
            "300": 315,
            "200": 44,
            "100": 11,
            "50": 6,
            "0": 15
        },
        "6701104241008065452": {
            "uid": 6701104,
            "bid": 4705178,
            "time": "241008065452",
            "mods": [
                "DT",
                "CL"
            ],
            "combo": 130,
            "passed": true,
            "pp": 33.9295,
            "acc": 0.9175491679273827,
            "grade": "A",
            "score": 621755,
            "320": 258,
            "300": 314,
            "200": 48,
            "100": 6,
            "50": 3,
            "0": 32
        },
        "6701104241009125800": {
            "uid": 6701104,
            "bid": 2759264,
            "time": "241009125800",
            "mods": [
                "CL"
            ],
            "combo": 378,
            "passed": true,
            "pp": null,
            "acc": 0.9236533009315512,
            "grade": "A",
            "score": 659582,
            "320": 846,
            "300": 582,
            "200": 123,
            "100": 21,
            "50": 20,
            "0": 54
        }
    }
}