{
    "id": 8023063,
    "name": "Gundham",
    "avatar url": "https://a.ppy.sh/8023063?1697825926.jpeg",
    "days ago": 0,
    "tracking": true,
    "beatmapsets": {},
    "beatmap plays history": {},
    "scores": {
        "8023063240930200323": {
            "uid": 8023063,
            "bid": 4705176,
            "time": "240930200323",
            "mods": [
                "CL"
            ],
            "combo": 93,
            "passed": true,
            "pp": 9.69335,
            "acc": 0.9255050505050505,
            "grade": "A",
            "score": 690492,
            "320": 242,
            "300": 114,
            "200": 12,
            "100": 6,
            "50": 3,
            "0": 19
        }
    }
}