{
    "id": 8985153,
    "name": "Male Parent",
    "avatar url": "https://a.ppy.sh/8985153?1729784143.png",
    "days ago": 0,
    "tracking": true,
    "beatmapsets": {},
    "beatmap plays history": {},
    "scores": {
        "8985153240929043657": {
            "uid": 8985153,
            "bid": 4705175,
            "time": "240929043657",
            "mods": [
                "CL"
            ],
            "combo": 783,
            "passed": true,
            "pp": 72.9349,
            "acc": 0.9920116194625999,
            "grade": "S",
            "score": 963078,
            "320": 727,
            "300": 176,
            "200": 11,
            "100": 0,
            "50": 2,
            "0": 2
        },
        "8985153240929044655": {
            "uid": 8985153,
            "bid": 4705176,
            "time": "240929044655",
            "mods": [
                "PF",
                "CL"
            ],
            "combo": 533,
            "passed": true,
            "pp": 18.0108,
            "acc": 1.0,
            "grade": "X",
            "score": 998343,
            "320": 375,
            "300": 21,
            "200": 0,
            "100": 0,
            "50": 0,
            "0": 0
        },
        "8985153240929042849": {
            "uid": 8985153,
            "bid": 4705177,
            "time": "240929042849",
            "mods": [
                "CL"
            ],
            "combo": 469,
            "passed": true,
            "pp": 110.79,
            "acc": 0.9572683706070287,
            "grade": "S",
            "score": 807541,
            "320": 788,
            "300": 353,
            "200": 79,
            "100": 13,
            "50": 3,
            "0": 16
        },
        "8985153241010083729": {
            "uid": 8985153,
            "bid": 4705177,
            "time": "241010083729",
            "mods": [
                "CL"
            ],
            "combo": 368,
            "passed": true,
            "pp": 107.171,
            "acc": 0.9531416400425985,
            "grade": "S",
            "score": 777608,
            "320": 776,
            "300": 365,
            "200": 68,
            "100": 18,
            "50": 6,
            "0": 19
        },
        "8985153240929042649": {
            "uid": 8985153,
            "bid": 4705177,
            "time": "240929042649",
            "mods": [
                "MR",
                "CL"
            ],
            "combo": 310,
            "passed": true,
            "pp": 98.0329,
            "acc": 0.9427582534611288,
            "grade": "A",
            "score": 762743,
            "320": 745,
            "300": 366,
            "200": 92,
            "100": 19,
            "50": 10,
            "0": 20
        },
        "8985153241004032911": {
            "uid": 8985153,
            "bid": 4705178,
            "time": "241004032911",
            "mods": [
                "SD",
                "CL"
            ],
            "combo": 972,
            "passed": true,
            "pp": 39.1098,
            "acc": 0.9984871406959153,
            "grade": "S",
            "score": 994310,
            "320": 585,
            "300": 73,
            "200": 3,
            "100": 0,
            "50": 0,
            "0": 0
        },
        "8985153240929044004": {
            "uid": 8985153,
            "bid": 4705178,
            "time": "240929044004",
            "mods": [
                "CL"
            ],
            "combo": 634,
            "passed": true,
            "pp": 38.9746,
            "acc": 0.9979828542612204,
            "grade": "S",
            "score": 993601,
            "320": 583,
            "300": 74,
            "200": 4,
            "100": 0,
            "50": 0,
            "0": 0
        },
        "8985153241010073958": {
            "uid": 8985153,
            "bid": 2759258,
            "time": "241010073958",
            "mods": [
                "CL"
            ],
            "combo": 298,
            "passed": true,
            "pp": null,
            "acc": 0.9251936068545065,
            "grade": "A",
            "score": 723444,
            "320": 1135,
            "300": 604,
            "200": 167,
            "100": 60,
            "50": 8,
            "0": 49
        },
        "8985153241009151151": {
            "uid": 8985153,
            "bid": 2759258,
            "time": "241009151151",
            "mods": [
                "CL"
            ],
            "combo": 247,
            "passed": true,
            "pp": null,
            "acc": 0.921403855659911,
            "grade": "A",
            "score": 682386,
            "320": 1142,
            "300": 581,
            "200": 186,
            "100": 46,
            "50": 10,
            "0": 58
        },
        "8985153241009150902": {
            "uid": 8985153,
            "bid": 2759262,
            "time": "241009150902",
            "mods": [
                "CL"
            ],
            "combo": 571,
            "passed": true,
            "pp": null,
            "acc": 0.9562056737588652,
            "grade": "S",
            "score": 825526,
            "320": 620,
            "300": 248,
            "200": 40,
            "100": 10,
            "50": 5,
            "0": 17
        },
        "8985153241010073643": {
            "uid": 8985153,
            "bid": 2759263,
            "time": "241010073643",
            "mods": [
                "CL"
            ],
            "combo": 615,
            "passed": true,
            "pp": null,
            "acc": 0.9541469402069086,
            "grade": "S",
            "score": 771434,
            "320": 990,
            "300": 719,
            "200": 146,
            "100": 20,
            "50": 5,
            "0": 21
        },
        "8985153241010073349": {
            "uid": 8985153,
            "bid": 2759263,
            "time": "241010073349",
            "mods": [
                "CL"
            ],
            "combo": 458,
            "passed": true,
            "pp": null,
            "acc": 0.951779765035946,
            "grade": "S",
            "score": 758123,
            "320": 984,
            "300": 725,
            "200": 131,
            "100": 35,
            "50": 8,
            "0": 18
        },
        "8985153241010073045": {
            "uid": 8985153,
            "bid": 2759263,
            "time": "241010073045",
            "mods": [
                "CL"
            ],
            "combo": 606,
            "passed": true,
            "pp": null,
            "acc": 0.9490618972470629,
            "grade": "A",
            "score": 759513,
            "320": 1000,
            "300": 690,
            "200": 151,
            "100": 38,
            "50": 5,
            "0": 17
        },
        "8985153241009150647": {
            "uid": 8985153,
            "bid": 2759263,
            "time": "241009150647",
            "mods": [
                "CL"
            ],
            "combo": 355,
            "passed": true,
            "pp": null,
            "acc": 0.9457303173768192,
            "grade": "A",
            "score": 733589,
            "320": 1039,
            "300": 625,
            "200": 182,
            "100": 34,
            "50": 7,
            "0": 14
        },
        "8985153241009150407": {
            "uid": 8985153,
            "bid": 2759264,
            "time": "241009150407",
            "mods": [
                "CL"
            ],
            "combo": 403,
            "passed": true,
            "pp": null,
            "acc": 0.9441069258809235,
            "grade": "A",
            "score": 760169,
            "320": 978,
            "300": 488,
            "200": 118,
            "100": 24,
            "50": 8,
            "0": 30
        },
        "8985153241010075410": {
            "uid": 8985153,
            "bid": 2759269,
            "time": "241010075410",
            "mods": [
                "CL"
            ],
            "combo": 679,
            "passed": true,
            "pp": null,
            "acc": 0.9475012309207287,
            "grade": "A",
            "score": 767624,
            "320": 1712,
            "300": 790,
            "200": 87,
            "100": 13,
            "50": 9,
            "0": 97
        },
        "8985153241010074905": {
            "uid": 8985153,
            "bid": 2759269,
            "time": "241010074905",
            "mods": [
                "CL"
            ],
            "combo": 572,
            "passed": true,
            "pp": null,
            "acc": 0.9493476120137863,
            "grade": "A",
            "score": 758773,
            "320": 1741,
            "300": 777,
            "200": 69,
            "100": 18,
            "50": 5,
            "0": 98
        },
        "8985153241010074515": {
            "uid": 8985153,
            "bid": 2759269,
            "time": "241010074515",
            "mods": [
                "CL"
            ],
            "combo": 377,
            "passed": true,
            "pp": null,
            "acc": 0.9415312653865091,
            "grade": "A",
            "score": 732528,
            "320": 1828,
            "300": 659,
            "200": 87,
            "100": 12,
            "50": 4,
            "0": 118
        },
        "8985153241009151746": {
            "uid": 8985153,
            "bid": 2759269,
            "time": "241009151746",
            "mods": [
                "CL"
            ],
            "combo": 204,
            "passed": true,
            "pp": null,
            "acc": 0.9205440669620877,
            "grade": "A",
            "score": 676798,
            "320": 1561,
            "300": 808,
            "200": 162,
            "100": 39,
            "50": 17,
            "0": 121
        },
        "8985153241010085712": {
            "uid": 8985153,
            "bid": 2759274,
            "time": "241010085712",
            "mods": [
                "CL"
            ],
            "combo": 589,
            "passed": true,
            "pp": null,
            "acc": 0.8958958958958959,
            "grade": "B",
            "score": 643120,
            "320": 413,
            "300": 394,
            "200": 108,
            "100": 40,
            "50": 16,
            "0": 28
        },
        "8985153241010074148": {
            "uid": 8985153,
            "bid": 2759274,
            "time": "241010074148",
            "mods": [
                "CL"
            ],
            "combo": 363,
            "passed": true,
            "pp": null,
            "acc": 0.8987320653987321,
            "grade": "B",
            "score": 618284,
            "320": 426,
            "300": 392,
            "200": 101,
            "100": 27,
            "50": 21,
            "0": 32
        },
        "8985153241009151427": {
            "uid": 8985153,
            "bid": 2759274,
            "time": "241009151427",
            "mods": [
                "CL"
            ],
            "combo": 413,
            "passed": true,
            "pp": null,
            "acc": 0.8938938938938938,
            "grade": "B",
            "score": 601749,
            "320": 440,
            "300": 377,
            "200": 98,
            "100": 23,
            "50": 18,
            "0": 43
        }
    }
}