{
    "id": 13575113,
    "name": "osotron2000",
    "avater url": "https://a.ppy.sh/13575113?1742876458.png",
    "days ago": 0,
    "tracking": true,
    "beatmapsets": {},
    "beatmap plays history": {},
    "lb beatmap plays history": {},
    "scores": {
        "13575113042025052823": {
            "uid": 13575113,
            "bid": 4971712,
            "time": "042025052823",
            "mods": [],
            "combo": 355,
            "passed": true,
            "pp": 24.7492,
            "acc": 0.9643939393939394,
            "grade": "S",
            "score": 818007,
            "320": 988,
            "300": 451,
            "200": 60,
            "100": 14,
            "50": 9,
            "0": 18
        },
        "13575113042025052344": {
            "uid": 13575113,
            "bid": 4971712,
            "time": "042025052344",
            "mods": [],
            "combo": 222,
            "passed": true,
            "pp": 23.0219,
            "acc": 0.9527056277056277,
            "grade": "S",
            "score": 783501,
            "320": 1010,
            "300": 401,
            "200": 74,
            "100": 12,
            "50": 17,
            "0": 26
        },
        "13575113041225024129": {
            "uid": 13575113,
            "bid": 4971712,
            "time": "041225024129",
            "mods": [],
            "combo": 165,
            "passed": true,
            "pp": 20.1246,
            "acc": 0.9373376623376624,
            "grade": "A",
            "score": 728333,
            "320": 949,
            "300": 424,
            "200": 92,
            "100": 18,
            "50": 19,
            "0": 38
        }
    }
}